cli/main.py
typer_test_demo-2.0.dist-info/METADATA
typer_test_demo-2.0.dist-info/WHEEL
typer_test_demo-2.0.dist-info/entry_points.txt
typer_test_demo-2.0.dist-info/top_level.txt
typer_test_demo-2.0.dist-info/RECORD
