Metadata-Version: 2.1
Name: typer-test-demo
Version: 2.0
Requires-Dist: typer
